precisely/__init__.py
precisely/base.py
precisely/coercion.py
precisely/comparison_matchers.py
precisely/core_matchers.py
precisely/feature_matchers.py
precisely/function_matchers.py
precisely/hamcrest.py
precisely/iterable_matchers.py
precisely/mapping_matchers.py
precisely/object_matchers.py
precisely/results.py
precisely-0.1.9.dist-info/LICENSE
precisely-0.1.9.dist-info/METADATA
precisely-0.1.9.dist-info/WHEEL
precisely-0.1.9.dist-info/top_level.txt
precisely-0.1.9.dist-info/RECORD
