Metadata-Version: 1.2
Name: precisely
Version: 0.1.9
Summary: Rich matchers, useful for assertions in tests. Inspired by Hamcrest.
Home-page: http://github.com/mwilliamson/python-precisely
Author: Michael Williamson
Author-email: mike@zwobble.org
License: BSD-2-Clause
Keywords: matcher matchers
Platform: UNKNOWN
Classifier: Development Status :: 5 - Production/Stable
Classifier: Intended Audience :: Developers
Classifier: License :: OSI Approved :: BSD License
Classifier: Programming Language :: Python
Classifier: Programming Language :: Python :: 2
Classifier: Programming Language :: Python :: 2.7
Classifier: Programming Language :: Python :: 3
Classifier: Programming Language :: Python :: 3.4
Classifier: Programming Language :: Python :: 3.5
Classifier: Programming Language :: Python :: 3.6
Classifier: Programming Language :: Python :: 3.7
Classifier: Programming Language :: Python :: 3.8
Classifier: Programming Language :: Python :: 3.9
Requires-Python: >=2.7, !=3.0.*, !=3.1.*, !=3.2.*, !=3.3.*
